LICENCE.txt
MANIFEST.in
README.rst
setup.py
PyWiki2xhtml/ABOUT
PyWiki2xhtml/COPYING
PyWiki2xhtml/__init__.py
PyWiki2xhtml/acronyms.txt
PyWiki2xhtml/flat2tree.py
PyWiki2xhtml/helper.py
PyWiki2xhtml/make_doc.sh
PyWiki2xhtml/parser.py
PyWiki2xhtml/test.py
PyWiki2xhtml.egg-info/PKG-INFO
PyWiki2xhtml.egg-info/SOURCES.txt
PyWiki2xhtml.egg-info/dependency_links.txt
PyWiki2xhtml.egg-info/not-zip-safe
PyWiki2xhtml.egg-info/top_level.txt
PyWiki2xhtml/macros/__init__.py
PyWiki2xhtml/macros/helper.py
PyWiki2xhtml/macros/macro_attach.py
PyWiki2xhtml/macros/macro_gmap.py
PyWiki2xhtml/macros/macro_mediaplayer.py
PyWiki2xhtml/macros/macro_pygments.py
PyWiki2xhtml/macros/parser.py
PyWiki2xhtml/macros/test.py
PyWiki2xhtml/testcases/__init__.py
PyWiki2xhtml/testcases/default.py
PyWiki2xhtml/testcases/macros.py
PyWiki2xhtml/wikibar/README
PyWiki2xhtml/wikibar/api.js
PyWiki2xhtml/wikibar/fake_help.html
PyWiki2xhtml/wikibar/test.html
PyWiki2xhtml/wikibar/test_customized.html
PyWiki2xhtml/wikibar/test_full.html
PyWiki2xhtml/wikibar/ui.css
PyWiki2xhtml/wikibar/images/attach.png
PyWiki2xhtml/wikibar/images/bullet_list.png
PyWiki2xhtml/wikibar/images/help.png
PyWiki2xhtml/wikibar/images/image.png
PyWiki2xhtml/wikibar/images/number_list.png
PyWiki2xhtml/wikibar/images/reminders.png
PyWiki2xhtml/wikibar/images/text_bold.png
PyWiki2xhtml/wikibar/images/text_code.png
PyWiki2xhtml/wikibar/images/text_h2.png
PyWiki2xhtml/wikibar/images/text_h3.png
PyWiki2xhtml/wikibar/images/text_h4.png
PyWiki2xhtml/wikibar/images/text_instant.png
PyWiki2xhtml/wikibar/images/text_italic.png
PyWiki2xhtml/wikibar/images/text_link.png
PyWiki2xhtml/wikibar/images/text_strike.png
PyWiki2xhtml/wikibar/images/text_teletype.png
PyWiki2xhtml/wikibar/images/text_under.png
PyWiki2xhtml/wikibar/images/text_wikiword.png
PyWiki2xhtml/wikibar/images/video.png
PyWiki2xhtml/wikibar/images/wikibar_icon.xcf