Metadata-Version: 1.0
Name: PyWiki2xhtml
Version: 1.8.4
Summary: PyWiki2Xhtml, a python transformer from Wiki syntax to XHTML
Home-page: UNKNOWN
Author: Thenon David
Author-email: sveetch AT gmail.com
License: GPL
Platform: UNKNOWN
Classifier: Programming Language :: Python
Classifier: License :: OSI Approved :: MIT License
Classifier: Operating System :: OS Independent
Classifier: Development Status :: 7 - Inactive
Classifier: Environment :: Web Environment
Classifier: Intended Audience :: Developers
Classifier: Topic :: Internet :: WWW/HTTP
Classifier: Topic :: Software Development :: Libraries :: Python Modules
